[{
    "limit":"5",
"name": "Anime1",
    "author": "Ineffable",
    "url": "https://raw.githubusercontent.com/ineffablexd/10k/main/Soft anime_13.webp",
    "thumbnail": "https://raw.githubusercontent.com/ineffablexd/10k/main/Soft anime_13.webp",
    "dimensions": "1280x720",
    "collections": "Anime"
    },
    {
"name": "Anime6",
    "author": "Ineffable",
    "url": "https://raw.githubusercontent.com/ineffablexd/10k/main/Soft anime_12.webp",
    "thumbnail": "https://raw.githubusercontent.com/ineffablexd/10k/main/Soft anime_12.webp",
    "dimensions": "1280x720",
    "collections": "Anime"
    },{
"name": "Anime5",
    "author": "Ineffable",
    "url": "https://raw.githubusercontent.com/ineffablexd/10k/main/Soft anime_14.webp",
    "thumbnail": "https://raw.githubusercontent.com/ineffablexd/10k/main/Soft anime_14.webp",
    "dimensions": "1280x720",
    "collections": "Anime"
    },{
"name": "Anime4",
    "author": "Ineffable",
    "url": "https://raw.githubusercontent.com/ineffablexd/10k/main/Soft anime_12.webp",
    "thumbnail": "https://raw.githubusercontent.com/ineffablexd/10k/main/Soft anime_12.webp",
    "dimensions": "1280x720",
    "collections": "Anime"
    },{
"name": "Anime3",
    "author": "Ineffable",
    "url": "https://raw.githubusercontent.com/ineffablexd/10k/main/Soft anime_12.webp",
    "thumbnail": "https://raw.githubusercontent.com/ineffablexd/10k/main/Soft anime_12.webp",
    "dimensions": "1280x720",
    "collections": "Anime"
    },{
"name": "Anime2",
    "author": "Ineffable",
    "url": "https://raw.githubusercontent.com/ineffablexd/10k/main/Soft anime_15.webp",
    "thumbnail": "https://raw.githubusercontent.com/ineffablexd/10k/main/Soft anime_15.webp",
    "dimensions": "1280x720",
    "collections": "Anime"
    }
    
    ]
    
    
    
